{
  "entrypoints": [
    "main"
  ],
  "origins": {
    "38": [
      85,
      532,
      918,
      38
    ],
    "972": [
      972
    ],
    "17896441": [
      38,
      532,
      918
    ],
    "main": [
      303,
      532,
      179
    ],
    "runtime~main": [
      179,
      532,
      303
    ],
    "03641f9c": [
      862
    ],
    "08c4bdb5": [
      127
    ],
    "0e384e19": [
      671
    ],
    "14eb3368": [
      532,
      817
    ],
    "1be78505": [
      532,
      972
    ],
    "1f391b9e": [
      38,
      532,
      85
    ],
    "3152febb": [
      225
    ],
    "35ff62d2": [
      207
    ],
    "393be207": [
      414
    ],
    "4ba7e5a3": [
      735
    ],
    "51fbb950": [
      125
    ],
    "5a704560": [
      792
    ],
    "68c8927c": [
      517
    ],
    "7842881c": [
      915
    ],
    "935f2afb": [
      53
    ],
    "954383cb": [
      515
    ],
    "bc807ee1": [
      526
    ],
    "bff1418c": [
      755
    ],
    "c4de80f8": [
      943
    ],
    "c4f5d8e4": [
      532,
      195
    ],
    "f048aca1": [
      692
    ],
    "fe199a3d": [
      830
    ],
    "styles": [
      38,
      85,
      179,
      195,
      303,
      514,
      817,
      918,
      532
    ]
  },
  "assets": {
    "38": {
      "js": [
        {
          "file": "assets/js/38.8c707da2.js",
          "hash": "533bcd2c6f7870da",
          "publicPath": "/assets/js/38.8c707da2.js"
        }
      ]
    },
    "53": {
      "js": [
        {
          "file": "assets/js/935f2afb.9279e6ec.js",
          "hash": "c9b78c8799bfad7d",
          "publicPath": "/assets/js/935f2afb.9279e6ec.js"
        }
      ]
    },
    "85": {
      "js": [
        {
          "file": "assets/js/1f391b9e.d3c04fe8.js",
          "hash": "8bdf68d2b0f5a820",
          "publicPath": "/assets/js/1f391b9e.d3c04fe8.js"
        }
      ]
    },
    "125": {
      "js": [
        {
          "file": "assets/js/51fbb950.09f4fc32.js",
          "hash": "d0ca4d7b433d948e",
          "publicPath": "/assets/js/51fbb950.09f4fc32.js"
        }
      ]
    },
    "127": {
      "js": [
        {
          "file": "assets/js/08c4bdb5.5a5329a6.js",
          "hash": "4d91fc19593d49ae",
          "publicPath": "/assets/js/08c4bdb5.5a5329a6.js"
        }
      ]
    },
    "179": {
      "js": [
        {
          "file": "assets/js/main.b3ae1a38.js",
          "hash": "4fd1498728e0913c",
          "publicPath": "/assets/js/main.b3ae1a38.js"
        }
      ]
    },
    "195": {
      "js": [
        {
          "file": "assets/js/c4f5d8e4.5dd1f372.js",
          "hash": "bf4ae1bd3a6bc9b9",
          "publicPath": "/assets/js/c4f5d8e4.5dd1f372.js"
        }
      ]
    },
    "207": {
      "js": [
        {
          "file": "assets/js/35ff62d2.51940dfc.js",
          "hash": "92e84860bd9d330e",
          "publicPath": "/assets/js/35ff62d2.51940dfc.js"
        }
      ]
    },
    "225": {
      "js": [
        {
          "file": "assets/js/3152febb.938a4f13.js",
          "hash": "fec681f88754ecbf",
          "publicPath": "/assets/js/3152febb.938a4f13.js"
        }
      ]
    },
    "303": {
      "js": [
        {
          "file": "assets/js/runtime~main.a216cc5b.js",
          "hash": "c56828c2a395de26",
          "publicPath": "/assets/js/runtime~main.a216cc5b.js"
        }
      ]
    },
    "414": {
      "js": [
        {
          "file": "assets/js/393be207.b83f551e.js",
          "hash": "564d176c032df347",
          "publicPath": "/assets/js/393be207.b83f551e.js"
        }
      ]
    },
    "515": {
      "js": [
        {
          "file": "assets/js/954383cb.d40cefb2.js",
          "hash": "9e012e3c9ee2f4dd",
          "publicPath": "/assets/js/954383cb.d40cefb2.js"
        }
      ]
    },
    "517": {
      "js": [
        {
          "file": "assets/js/68c8927c.7f836094.js",
          "hash": "7b79447964dbfbf3",
          "publicPath": "/assets/js/68c8927c.7f836094.js"
        }
      ]
    },
    "526": {
      "js": [
        {
          "file": "assets/js/bc807ee1.53711a50.js",
          "hash": "9f8ea975a5a57a1f",
          "publicPath": "/assets/js/bc807ee1.53711a50.js"
        }
      ]
    },
    "532": {
      "css": [
        {
          "file": "assets/css/styles.65cc33c2.css",
          "hash": "032bfa808fe0fa70",
          "publicPath": "/assets/css/styles.65cc33c2.css"
        }
      ]
    },
    "671": {
      "js": [
        {
          "file": "assets/js/0e384e19.eb605b95.js",
          "hash": "4214b770bbfe26a5",
          "publicPath": "/assets/js/0e384e19.eb605b95.js"
        }
      ]
    },
    "692": {
      "js": [
        {
          "file": "assets/js/f048aca1.80f0f08c.js",
          "hash": "52f21361f4d01201",
          "publicPath": "/assets/js/f048aca1.80f0f08c.js"
        }
      ]
    },
    "735": {
      "js": [
        {
          "file": "assets/js/4ba7e5a3.bfddb08d.js",
          "hash": "cbc02aa39b89ed82",
          "publicPath": "/assets/js/4ba7e5a3.bfddb08d.js"
        }
      ]
    },
    "755": {
      "js": [
        {
          "file": "assets/js/bff1418c.8a62d7e8.js",
          "hash": "91e0191fa41cdfdc",
          "publicPath": "/assets/js/bff1418c.8a62d7e8.js"
        }
      ]
    },
    "792": {
      "js": [
        {
          "file": "assets/js/5a704560.a1f6df07.js",
          "hash": "a38038fb7f79a78e",
          "publicPath": "/assets/js/5a704560.a1f6df07.js"
        }
      ]
    },
    "817": {
      "js": [
        {
          "file": "assets/js/14eb3368.92abf66b.js",
          "hash": "7ee1e571317a4eaa",
          "publicPath": "/assets/js/14eb3368.92abf66b.js"
        }
      ]
    },
    "830": {
      "js": [
        {
          "file": "assets/js/fe199a3d.dc29fd41.js",
          "hash": "0390f36832d5a898",
          "publicPath": "/assets/js/fe199a3d.dc29fd41.js"
        }
      ]
    },
    "862": {
      "js": [
        {
          "file": "assets/js/03641f9c.2b592c26.js",
          "hash": "aa6354dcb33f6a55",
          "publicPath": "/assets/js/03641f9c.2b592c26.js"
        }
      ]
    },
    "915": {
      "js": [
        {
          "file": "assets/js/7842881c.162ad544.js",
          "hash": "975145a70966317c",
          "publicPath": "/assets/js/7842881c.162ad544.js"
        }
      ]
    },
    "918": {
      "js": [
        {
          "file": "assets/js/17896441.cf7ba8c9.js",
          "hash": "23391370df841ceb",
          "publicPath": "/assets/js/17896441.cf7ba8c9.js"
        }
      ]
    },
    "943": {
      "js": [
        {
          "file": "assets/js/c4de80f8.9808da33.js",
          "hash": "fd5e422b587a3159",
          "publicPath": "/assets/js/c4de80f8.9808da33.js"
        }
      ]
    },
    "972": {
      "js": [
        {
          "file": "assets/js/972.5058414f.js",
          "hash": "88808be5d3c6bf08",
          "publicPath": "/assets/js/972.5058414f.js"
        },
        {
          "file": "assets/js/1be78505.9ea16cc0.js",
          "hash": "b5264d9850134ec2",
          "publicPath": "/assets/js/1be78505.9ea16cc0.js"
        }
      ]
    }
  }
}
